{"http://sitoscope.naamii.org.np/media/stool/Loharpatti/2023-09-17/S_MP-loharpatti_20230917_GEP00/2/S_MP-loharpatti_20230917_GE_mgMPGzH.jpg-1":{"filename":"http://sitoscope.naamii.org.np/media/stool/Loharpatti/2023-09-17/S_MP-loharpatti_20230917_GEP00/2/S_MP-loharpatti_20230917_GE_mgMPGzH.jpg","size":-1,"regions":[{"shape_attributes":{"name":"rect","x":3622,"y":1502,"width":87,"height":87},"region_attributes":{"RECTANGLE":"Cryptosporidium"}},{"shape_attributes":{"name":"rect","x":902,"y":741,"width":80,"height":89},"region_attributes":{"RECTANGLE":"Cryptosporidium"}},{"shape_attributes":{"name":"rect","x":151,"y":1751,"width":83,"height":87},"region_attributes":{"RECTANGLE":"Cryptosporidium"}}],"file_attributes":{}}}